CHANGELOG.rst
LICENSE
MANIFEST.in
README.md
requirements.txt
setup.cfg
setup.py
tests-requirements.txt
fmn_sse/__init__.py
fmn_sse/server.py
fmn_sse.egg-info/PKG-INFO
fmn_sse.egg-info/SOURCES.txt
fmn_sse.egg-info/dependency_links.txt
fmn_sse.egg-info/not-zip-safe
fmn_sse.egg-info/requires.txt
fmn_sse.egg-info/top_level.txt
systemd/fmn-sse-python2@.service
systemd/fmn-sse-python3@.service