Metadata-Version: 1.1
Name: fmn-sse
Version: 0.2.1
Summary: Real time feed for fedmsg
Home-page: https://github.com/fedora-infra/fmn.sse/
Author: Fedora Infrastructure Team and Szymon M
Author-email: infrastructure@lists.fedoraproject.org
License: GPLv2+
Download-URL: https://pypi.python.org/pypi/fmn_sse/
Platform: UNKNOWN
Classifier: Development Status :: 3 - Alpha
Classifier: Environment :: Web Environment
Classifier: Framework :: Twisted
Classifier: Intended Audience :: Developers
Classifier: License :: OSI Approved :: GNU General Public License v2 or later (GPLv2+)
Classifier: Programming Language :: Python
Classifier: Programming Language :: Python :: 2
Classifier: Programming Language :: Python :: 2.7
Classifier: Programming Language :: Python :: 3
Classifier: Programming Language :: Python :: 3.4
Classifier: Programming Language :: Python :: 3.5
Classifier: Programming Language :: Python :: 3.6
Classifier: Topic :: Software Development :: Libraries :: Python Modules
